setup.py
getmole2/Get_molecule_h5_file.py
getmole2/__init__.py
getmole2.egg-info/PKG-INFO
getmole2.egg-info/SOURCES.txt
getmole2.egg-info/dependency_links.txt
getmole2.egg-info/not-zip-safe
getmole2.egg-info/top_level.txt