Metadata-Version: 1.0
Name: getmole2
Version: 0.1
Summary: get molecule file
Home-page: http://github.com/maiziex/getmole2
Author: maiziex
Author-email: maiziex@gmail.com
License: MIT
Platform: UNKNOWN
